README.md
pyproject.toml
kirgram/__init__.py
kirgram/client.py
kirgram/dispatcher.py
kirgram/emoji.py
kirgram/file_id.py
kirgram/filters.py
kirgram/mime_types.py
kirgram/py.typed
kirgram/qrlogin.py
kirgram/sync.py
kirgram/utils.py
kirgram/connection/__init__.py
kirgram/connection/connection.py
kirgram/connection/transport/__init__.py
kirgram/connection/transport/tcp/__init__.py
kirgram/connection/transport/tcp/tcp.py
kirgram/connection/transport/tcp/tcp_abridged.py
kirgram/connection/transport/tcp/tcp_abridged_o.py
kirgram/connection/transport/tcp/tcp_full.py
kirgram/connection/transport/tcp/tcp_intermediate.py
kirgram/connection/transport/tcp/tcp_intermediate_o.py
kirgram/crypto/__init__.py
kirgram/crypto/aes.py
kirgram/crypto/mtproto.py
kirgram/crypto/prime.py
kirgram/crypto/rsa.py
kirgram/enums/__init__.py
kirgram/enums/auto_name.py
kirgram/enums/business_schedule.py
kirgram/enums/chat_action.py
kirgram/enums/chat_event_action.py
kirgram/enums/chat_join_type.py
kirgram/enums/chat_member_status.py
kirgram/enums/chat_members_filter.py
kirgram/enums/chat_type.py
kirgram/enums/client_platform.py
kirgram/enums/folder_color.py
kirgram/enums/gift_attribute_type.py
kirgram/enums/gift_for_resale_order.py
kirgram/enums/media_area_type.py
kirgram/enums/message_entity_type.py
kirgram/enums/message_media_type.py
kirgram/enums/message_origin_type.py
kirgram/enums/message_service_type.py
kirgram/enums/messages_filter.py
kirgram/enums/next_code_type.py
kirgram/enums/paid_reaction_privacy.py
kirgram/enums/parse_mode.py
kirgram/enums/phone_call_discard_reason.py
kirgram/enums/poll_type.py
kirgram/enums/privacy_key.py
kirgram/enums/privacy_rule_type.py
kirgram/enums/profile_color.py
kirgram/enums/reply_color.py
kirgram/enums/sent_code_type.py
kirgram/enums/stories_privacy_rules.py
kirgram/enums/user_status.py
kirgram/errors/__init__.py
kirgram/errors/rpc_error.py
kirgram/errors/exceptions/__init__.py
kirgram/errors/exceptions/all.py
kirgram/errors/exceptions/bad_request_400.py
kirugram.egg-info/PKG-INFO
kirugram.egg-info/SOURCES.txt
kirugram.egg-info/dependency_links.txt
kirugram.egg-info/requires.txt
kirugram.egg-info/top_level.txt