Metadata-Version: 2.4
Name: kirugram
Version: 2.2.5
Summary: Kirgram is a Telegram client library for Python. It is a fork of Pyrogram.
Requires-Python: >=3.10
Requires-Dist: requests>=2.28.0
Requires-Dist: pyrogram>=2.0.0
